pyswitcher.py
pyswitcher-0.0.1.dist-info/METADATA
pyswitcher-0.0.1.dist-info/WHEEL
pyswitcher-0.0.1.dist-info/top_level.txt
pyswitcher-0.0.1.dist-info/RECORD
