Metadata-Version: 2.1
Name: pyswitcher
Version: 0.0.1
Summary: Switch/case for Python.
Home-page: UNKNOWN
Author: fjy
Author-email: p2589660302@qq.com
Maintainer: fjy
Maintainer-email: p2589660302@qq.com
License: UNKNOWN
Platform: UNKNOWN
